{
  "schemaVersion": 1,
  "generatedAt": "2026-06-10T20:46:10.759Z",
  "status": "partial",
  "purpose": "Split online tool metadata index for DevEnv Manager.",
  "summary": {
    "totalTools": 133,
    "totalPackageSources": 406,
    "totalScannedSources": 406
  },
  "tools": [
    {
      "id": "git",
      "name": "Git",
      "categoryId": "source-control",
      "platforms": [
        "windows",
        "macos",
        "linux"
      ],
      "sourceCount": 4,
      "bestQualityScore": 100,
      "path": "data/online/tools/git.json",
      "bytes": 40801,
      "sha256": "a800f34cf557915d1bcc0da4f3aab27ce409fd01acc5c350c96ebce0a2e77b65"
    },
    {
      "id": "github_cli",
      "name": "GitHub CLI",
      "categoryId": "source-control",
      "platforms": [
        "windows",
        "macos",
        "linux"
      ],
      "sourceCount": 5,
      "bestQualityScore": 100,
      "path": "data/online/tools/github_cli.json",
      "bytes": 93819,
      "sha256": "8afd676b80d1a5f1fac677b9c7a11075e9f409b0229a2a737139d5588493463e"
    },
    {
      "id": "git_lfs",
      "name": "Git LFS",
      "categoryId": "source-control",
      "platforms": [
        "windows",
        "macos",
        "linux"
      ],
      "sourceCount": 5,
      "bestQualityScore": 100,
      "path": "data/online/tools/git_lfs.json",
      "bytes": 89238,
      "sha256": "7607798970b0e7524b2f6115f73aecab3948835a359b97d121131cf0e84f4887"
    },
    {
      "id": "github_desktop",
      "name": "GitHub Desktop",
      "categoryId": "source-control",
      "platforms": [
        "windows",
        "macos"
      ],
      "sourceCount": 3,
      "bestQualityScore": 100,
      "path": "data/online/tools/github_desktop.json",
      "bytes": 34195,
      "sha256": "732fb09684b81d0f7ad96ec45eb2fa17e76a38cdd1c804e602e99b4f9bf99d99"
    },
    {
      "id": "git_extensions",
      "name": "Git Extensions",
      "categoryId": "source-control",
      "platforms": [
        "windows"
      ],
      "sourceCount": 1,
      "bestQualityScore": 100,
      "path": "data/online/tools/git_extensions.json",
      "bytes": 13224,
      "sha256": "2b625a32eb4fbbb17c2f1889078d04d0da526b1b3857286487145fb5df5cf264"
    },
    {
      "id": "tortoisegit",
      "name": "TortoiseGit",
      "categoryId": "source-control",
      "platforms": [
        "windows"
      ],
      "sourceCount": 1,
      "bestQualityScore": 65,
      "path": "data/online/tools/tortoisegit.json",
      "bytes": 7171,
      "sha256": "24e1e8aed6c7c3f5ceaa240bb91c2e2cf226eff3c8b42eca2d6ef8a35123e494"
    },
    {
      "id": "vscode",
      "name": "Visual Studio Code",
      "categoryId": "editor",
      "platforms": [
        "windows",
        "macos",
        "linux"
      ],
      "sourceCount": 5,
      "bestQualityScore": 100,
      "path": "data/online/tools/vscode.json",
      "bytes": 56367,
      "sha256": "22565960cdf2b71b001258040f534bb9db1c2bc6a9d6b7ed8df34ff925a6c736"
    },
    {
      "id": "vscodium",
      "name": "VSCodium",
      "categoryId": "editor",
      "platforms": [
        "windows",
        "macos",
        "linux"
      ],
      "sourceCount": 5,
      "bestQualityScore": 100,
      "path": "data/online/tools/vscodium.json",
      "bytes": 111661,
      "sha256": "35b657dc5b4b05333075870ab3c8aa5b1808471b9998182ed77f042007308fbc"
    },
    {
      "id": "jetbrains_toolbox",
      "name": "JetBrains Toolbox",
      "categoryId": "editor",
      "platforms": [
        "windows"
      ],
      "sourceCount": 1,
      "bestQualityScore": 100,
      "path": "data/online/tools/jetbrains_toolbox.json",
      "bytes": 15401,
      "sha256": "f5f0a2d8e75a3deaf92542552c7fffab87a5324da5a47f6909756bfff9a3053e"
    },
    {
      "id": "pycharm_community",
      "name": "PyCharm Community",
      "categoryId": "editor",
      "platforms": [
        "windows"
      ],
      "sourceCount": 1,
      "bestQualityScore": 100,
      "path": "data/online/tools/pycharm_community.json",
      "bytes": 15647,
      "sha256": "9f1c4187df08182aeccbeaf020462d1e327d9ac1672e2ee5d482d9a5eeeff45e"
    },
    {
      "id": "intellij_idea_community",
      "name": "IntelliJ IDEA Community",
      "categoryId": "editor",
      "platforms": [
        "windows"
      ],
      "sourceCount": 1,
      "bestQualityScore": 100,
      "path": "data/online/tools/intellij_idea_community.json",
      "bytes": 15888,
      "sha256": "928cd6a4be672f43a8a2773a9fd2f8660c9ba4693253c59ea01daa2e89a425cb"
    },
    {
      "id": "sublime_text",
      "name": "Sublime Text",
      "categoryId": "editor",
      "platforms": [
        "windows"
      ],
      "sourceCount": 1,
      "bestQualityScore": 100,
      "path": "data/online/tools/sublime_text.json",
      "bytes": 10349,
      "sha256": "1b68053c5292caf9cdf009687415ab7b15364e0da46e795b51d8dbd173002df2"
    },
    {
      "id": "notepad_plus_plus",
      "name": "Notepad++",
      "categoryId": "editor",
      "platforms": [
        "windows"
      ],
      "sourceCount": 1,
      "bestQualityScore": 100,
      "path": "data/online/tools/notepad_plus_plus.json",
      "bytes": 9742,
      "sha256": "f29d0bf1d7b7f97e4b72b27756cc5bda1cf927d607cddd76c196ded8391b264e"
    },
    {
      "id": "neovim",
      "name": "Neovim",
      "categoryId": "editor",
      "platforms": [
        "windows",
        "macos",
        "linux"
      ],
      "sourceCount": 5,
      "bestQualityScore": 100,
      "path": "data/online/tools/neovim.json",
      "bytes": 87406,
      "sha256": "358dae29ee48200123325b2f934d0792910f1cf9bea875e0558c4ad154078c7a"
    },
    {
      "id": "vim",
      "name": "Vim",
      "categoryId": "editor",
      "platforms": [
        "windows",
        "macos",
        "linux"
      ],
      "sourceCount": 4,
      "bestQualityScore": 100,
      "path": "data/online/tools/vim.json",
      "bytes": 40516,
      "sha256": "b32ccf246d8110498236417915540ed376d89c2fd037d9d18ba10b8510690f2a"
    },
    {
      "id": "emacs",
      "name": "GNU Emacs",
      "categoryId": "editor",
      "platforms": [
        "windows",
        "macos",
        "linux"
      ],
      "sourceCount": 4,
      "bestQualityScore": 100,
      "path": "data/online/tools/emacs.json",
      "bytes": 32326,
      "sha256": "60d10fee69f740e0e7190732b1dd60e279022c79222873332d23f5793be7ed9f"
    },
    {
      "id": "windows_terminal",
      "name": "Windows Terminal",
      "categoryId": "terminal",
      "platforms": [
        "windows"
      ],
      "sourceCount": 2,
      "bestQualityScore": 100,
      "path": "data/online/tools/windows_terminal.json",
      "bytes": 71822,
      "sha256": "d7f6a7e9def2297cb2fd5f8110062d268e3c94cb9f216b08cbf4b3dcf92a12c1"
    },
    {
      "id": "powershell",
      "name": "PowerShell 7",
      "categoryId": "terminal",
      "platforms": [
        "windows",
        "macos",
        "linux"
      ],
      "sourceCount": 5,
      "bestQualityScore": 100,
      "path": "data/online/tools/powershell.json",
      "bytes": 92945,
      "sha256": "c4e110a474538d2554046ac8c29db80b4f5b4270c7c88ded7f4a597eade840cc"
    },
    {
      "id": "oh_my_posh",
      "name": "Oh My Posh",
      "categoryId": "terminal",
      "platforms": [
        "windows",
        "macos",
        "linux"
      ],
      "sourceCount": 4,
      "bestQualityScore": 100,
      "path": "data/online/tools/oh_my_posh.json",
      "bytes": 84981,
      "sha256": "fb28081c39c947aefedcab2fab120fee47314d3917cb03845e17d4b24a692b9b"
    },
    {
      "id": "starship",
      "name": "Starship",
      "categoryId": "terminal",
      "platforms": [
        "windows",
        "macos",
        "linux"
      ],
      "sourceCount": 5,
      "bestQualityScore": 100,
      "path": "data/online/tools/starship.json",
      "bytes": 166310,
      "sha256": "5b5bc1191d438f519d71f1ee4f632cc8a0d26cc56f5d8ff95fc6078bd54cb57a"
    },
    {
      "id": "ripgrep",
      "name": "ripgrep",
      "categoryId": "terminal",
      "platforms": [
        "windows",
        "macos",
        "linux"
      ],
      "sourceCount": 5,
      "bestQualityScore": 100,
      "path": "data/online/tools/ripgrep.json",
      "bytes": 85587,
      "sha256": "0232db508b8c1b376f66d26058e98504f99429e421fda97478de45ddd7fbdf22"
    },
    {
      "id": "fd",
      "name": "fd",
      "categoryId": "terminal",
      "platforms": [
        "windows",
        "macos",
        "linux"
      ],
      "sourceCount": 5,
      "bestQualityScore": 100,
      "path": "data/online/tools/fd.json",
      "bytes": 83211,
      "sha256": "b52f21f452d59e20c711e9eaf1ec854d1338042103d59cae8beebcb992444854"
    },
    {
      "id": "bat",
      "name": "bat",
      "categoryId": "terminal",
      "platforms": [
        "windows",
        "macos",
        "linux"
      ],
      "sourceCount": 5,
      "bestQualityScore": 100,
      "path": "data/online/tools/bat.json",
      "bytes": 80981,
      "sha256": "246738e7609943103e83b76cb52915082e41c68c8530726afea08f65604bd983"
    },
    {
      "id": "fzf",
      "name": "fzf",
      "categoryId": "terminal",
      "platforms": [
        "windows",
        "macos",
        "linux"
      ],
      "sourceCount": 5,
      "bestQualityScore": 100,
      "path": "data/online/tools/fzf.json",
      "bytes": 88212,
      "sha256": "902d901606ce4fe8f64c193e15c4001c4593208ee8c31c674a2a7258f119ae39"
    },
    {
      "id": "jq",
      "name": "jq",
      "categoryId": "terminal",
      "platforms": [
        "windows",
        "macos",
        "linux"
      ],
      "sourceCount": 5,
      "bestQualityScore": 100,
      "path": "data/online/tools/jq.json",
      "bytes": 67238,
      "sha256": "b28450f86baffb0a4b5961474e13f6a73207a8ad8aec206045b29a11f11fe308"
    },
    {
      "id": "zoxide",
      "name": "zoxide",
      "categoryId": "terminal",
      "platforms": [
        "windows",
        "macos",
        "linux"
      ],
      "sourceCount": 5,
      "bestQualityScore": 100,
      "path": "data/online/tools/zoxide.json",
      "bytes": 83465,
      "sha256": "2c6850877b570ea21109cab6cd2f6ff1a121684082406672b31e9ab37d128c08"
    },
    {
      "id": "node_lts",
      "name": "Node.js LTS",
      "categoryId": "javascript",
      "platforms": [
        "windows"
      ],
      "sourceCount": 3,
      "bestQualityScore": 100,
      "path": "data/online/tools/node_lts.json",
      "bytes": 29313,
      "sha256": "10ce72784564dc59271c43995bf9af239329e90455b5002eecff4dc9de50768d"
    },
    {
      "id": "node_current",
      "name": "Node.js Current",
      "categoryId": "javascript",
      "platforms": [
        "windows",
        "macos",
        "linux"
      ],
      "sourceCount": 4,
      "bestQualityScore": 100,
      "path": "data/online/tools/node_current.json",
      "bytes": 41936,
      "sha256": "20dd198afada5d3391b5335bfa6fa2fef29b1262c276657970e141940140c0e6"
    },
    {
      "id": "npm",
      "name": "npm",
      "categoryId": "javascript",
      "platforms": [
        "windows"
      ],
      "sourceCount": 1,
      "bestQualityScore": 100,
      "path": "data/online/tools/npm.json",
      "bytes": 10285,
      "sha256": "7a6f8f9a89915ac88b7c7a3afd94a38c27fac87028d27c4138a6c1e77b7efd30"
    },
    {
      "id": "pnpm",
      "name": "pnpm",
      "categoryId": "javascript",
      "platforms": [
        "windows",
        "macos",
        "linux"
      ],
      "sourceCount": 4,
      "bestQualityScore": 100,
      "path": "data/online/tools/pnpm.json",
      "bytes": 40512,
      "sha256": "b4a463395652dcd42a2c565fdc956a1a7488112cbcc8497bae20275770644bb6"
    },
    {
      "id": "yarn",
      "name": "Yarn",
      "categoryId": "javascript",
      "platforms": [
        "windows",
        "macos",
        "linux"
      ],
      "sourceCount": 4,
      "bestQualityScore": 100,
      "path": "data/online/tools/yarn.json",
      "bytes": 34241,
      "sha256": "30c9a9b4a7cbe6d51322f067b939c8149c5262de19b5bb5da7d1503f05f6fffe"
    },
    {
      "id": "bun",
      "name": "Bun",
      "categoryId": "javascript",
      "platforms": [
        "windows",
        "macos",
        "linux"
      ],
      "sourceCount": 5,
      "bestQualityScore": 100,
      "path": "data/online/tools/bun.json",
      "bytes": 88367,
      "sha256": "80830240d4fbff713d499d1ea1f91e40931ba172371d1b78687ce23c24330f03"
    },
    {
      "id": "deno",
      "name": "Deno",
      "categoryId": "javascript",
      "platforms": [
        "windows",
        "macos",
        "linux"
      ],
      "sourceCount": 5,
      "bestQualityScore": 100,
      "path": "data/online/tools/deno.json",
      "bytes": 90450,
      "sha256": "fcf73e853ab9526b5e402689bd13d46cc0b7207c3ecf27e39ca2ec1961da3784"
    },
    {
      "id": "volta",
      "name": "Volta",
      "categoryId": "javascript",
      "platforms": [
        "windows",
        "macos",
        "linux"
      ],
      "sourceCount": 5,
      "bestQualityScore": 100,
      "path": "data/online/tools/volta.json",
      "bytes": 74748,
      "sha256": "598b36d5d879cafaa25edcfc7026e6cb0ff271e76478cf25f50900046f89fead"
    },
    {
      "id": "nvm_windows",
      "name": "nvm-windows",
      "categoryId": "javascript",
      "platforms": [
        "windows"
      ],
      "sourceCount": 4,
      "bestQualityScore": 100,
      "path": "data/online/tools/nvm_windows.json",
      "bytes": 68841,
      "sha256": "6a988f015eb6610e8858029bfa6f76c7c0dff3dea1911bb43ac1d1df075807c6"
    },
    {
      "id": "python_312",
      "name": "Python 3.12",
      "categoryId": "python",
      "platforms": [
        "windows",
        "macos",
        "linux"
      ],
      "sourceCount": 4,
      "bestQualityScore": 100,
      "path": "data/online/tools/python_312.json",
      "bytes": 35404,
      "sha256": "a27c5a1ec860e6c2b22a80429c076179f7c0c3c6b31437f88d2447a32906e88b"
    },
    {
      "id": "python_311",
      "name": "Python 3.11",
      "categoryId": "python",
      "platforms": [
        "windows",
        "macos",
        "linux"
      ],
      "sourceCount": 4,
      "bestQualityScore": 100,
      "path": "data/online/tools/python_311.json",
      "bytes": 30810,
      "sha256": "1e477445239ee7f7f8104dca833a9eacedcfb4cd1fd911955c32cfed34a00c45"
    },
    {
      "id": "uv",
      "name": "uv",
      "categoryId": "python",
      "platforms": [
        "windows",
        "macos",
        "linux"
      ],
      "sourceCount": 5,
      "bestQualityScore": 100,
      "path": "data/online/tools/uv.json",
      "bytes": 88629,
      "sha256": "e9e773dd13ba03189fee6982d05b53e1edbd45db2116d8a22ce424e6cb938a11"
    },
    {
      "id": "pipx",
      "name": "pipx",
      "categoryId": "python",
      "platforms": [
        "windows",
        "macos",
        "linux"
      ],
      "sourceCount": 2,
      "bestQualityScore": 100,
      "path": "data/online/tools/pipx.json",
      "bytes": 11395,
      "sha256": "d5bc937a096c0b44a10c331a5dc1438b8a1768996dfcea97eb8fe17374c8a5e8"
    },
    {
      "id": "poetry",
      "name": "Poetry",
      "categoryId": "python",
      "platforms": [
        "windows",
        "macos",
        "linux"
      ],
      "sourceCount": 3,
      "bestQualityScore": 100,
      "path": "data/online/tools/poetry.json",
      "bytes": 51423,
      "sha256": "da2086f693da9092625aee997c8e2d25695bc9052991c5ff19b9218effec0218"
    },
    {
      "id": "miniconda",
      "name": "Miniconda",
      "categoryId": "python",
      "platforms": [
        "windows",
        "macos"
      ],
      "sourceCount": 4,
      "bestQualityScore": 100,
      "path": "data/online/tools/miniconda.json",
      "bytes": 30480,
      "sha256": "343997a1b4e358d52c39a265dae3eb2bc503aaf8488fd0044e4e1ed2a0bdab83"
    },
    {
      "id": "anaconda",
      "name": "Anaconda",
      "categoryId": "python",
      "platforms": [
        "windows"
      ],
      "sourceCount": 1,
      "bestQualityScore": 100,
      "path": "data/online/tools/anaconda.json",
      "bytes": 11657,
      "sha256": "6afdd3a3d7e5f8603bb6cf7a7c9562954f87f1df7b2c153f39ce052fe7676b82"
    },
    {
      "id": "rustup",
      "name": "Rustup",
      "categoryId": "rust",
      "platforms": [
        "windows",
        "macos",
        "linux"
      ],
      "sourceCount": 4,
      "bestQualityScore": 100,
      "path": "data/online/tools/rustup.json",
      "bytes": 25616,
      "sha256": "dc3cba3cb1dc0861f0bcfcb8055dca485c98eb0da647f8e3d15ceb158852293d"
    },
    {
      "id": "rust_msvc",
      "name": "Rust MSVC",
      "categoryId": "rust",
      "platforms": [
        "windows"
      ],
      "sourceCount": 1,
      "bestQualityScore": 100,
      "path": "data/online/tools/rust_msvc.json",
      "bytes": 15568,
      "sha256": "87e99e1f0c3ef422b28fbbc41be5f18662b517b6acd1694957a1bcbf0934f641"
    },
    {
      "id": "cargo",
      "name": "Cargo",
      "categoryId": "rust",
      "platforms": [
        "windows"
      ],
      "sourceCount": 1,
      "bestQualityScore": 100,
      "path": "data/online/tools/cargo.json",
      "bytes": 11177,
      "sha256": "88fbd7c5818c1fd9a346074d7dc82b6c0c67b0f3f390748e64f4427cda8d365f"
    },
    {
      "id": "go",
      "name": "Go",
      "categoryId": "go",
      "platforms": [
        "windows",
        "macos",
        "linux"
      ],
      "sourceCount": 4,
      "bestQualityScore": 100,
      "path": "data/online/tools/go.json",
      "bytes": 40601,
      "sha256": "7f09b168fde554af3e9635ded4c51764307206a5be982f968ecf1c808ed3760d"
    },
    {
      "id": "tinygo",
      "name": "TinyGo",
      "categoryId": "go",
      "platforms": [
        "windows",
        "macos",
        "linux"
      ],
      "sourceCount": 2,
      "bestQualityScore": 100,
      "path": "data/online/tools/tinygo.json",
      "bytes": 56696,
      "sha256": "92855a1946368a99b5d510d80c7e693935b232005412e54699eda1534185d305"
    },
    {
      "id": "dotnet_9",
      "name": ".NET SDK 9",
      "categoryId": "dotnet",
      "platforms": [
        "windows"
      ],
      "sourceCount": 1,
      "bestQualityScore": 100,
      "path": "data/online/tools/dotnet_9.json",
      "bytes": 15900,
      "sha256": "1dc27b12a5d6a50e5fc0832f58031efe01a9de87834ccfce4aedf8e930465d6d"
    },
    {
      "id": "dotnet_8",
      "name": ".NET SDK 8",
      "categoryId": "dotnet",
      "platforms": [
        "windows"
      ],
      "sourceCount": 1,
      "bestQualityScore": 100,
      "path": "data/online/tools/dotnet_8.json",
      "bytes": 15900,
      "sha256": "1c46c4bc85c815b21746e37f64cc846d414bb8a6ef4de0ceda449e530e1a6e21"
    },
    {
      "id": "temurin_21",
      "name": "Eclipse Temurin JDK 21",
      "categoryId": "java",
      "platforms": [
        "windows",
        "macos"
      ],
      "sourceCount": 4,
      "bestQualityScore": 100,
      "path": "data/online/tools/temurin_21.json",
      "bytes": 32234,
      "sha256": "1e90ee0ca85be92ae5a3701f7ad0838e981851f7165d20a58331dc009e921762"
    },
    {
      "id": "temurin_17",
      "name": "Eclipse Temurin JDK 17",
      "categoryId": "java",
      "platforms": [
        "windows",
        "macos"
      ],
      "sourceCount": 4,
      "bestQualityScore": 100,
      "path": "data/online/tools/temurin_17.json",
      "bytes": 37552,
      "sha256": "352636e1de3969c4faf0b3a052697f80cabfaf907fbeae55a2de4fd78f661b87"
    },
    {
      "id": "oracle_jdk_21",
      "name": "Oracle JDK 21",
      "categoryId": "java",
      "platforms": [
        "windows"
      ],
      "sourceCount": 1,
      "bestQualityScore": 100,
      "path": "data/online/tools/oracle_jdk_21.json",
      "bytes": 9917,
      "sha256": "cf4f7dc1a7330752e99240907e9f7dcae57e08f841f446f7b48d7e56cf66e32e"
    },
    {
      "id": "maven",
      "name": "Apache Maven",
      "categoryId": "java",
      "platforms": [
        "windows",
        "macos",
        "linux"
      ],
      "sourceCount": 3,
      "bestQualityScore": 100,
      "path": "data/online/tools/maven.json",
      "bytes": 25971,
      "sha256": "37994930de16d2f3fdf87cba612961a1ac4e7f61b4a4efda389376c6ded49b75"
    },
    {
      "id": "gradle",
      "name": "Gradle",
      "categoryId": "java",
      "platforms": [
        "windows",
        "macos",
        "linux"
      ],
      "sourceCount": 3,
      "bestQualityScore": 100,
      "path": "data/online/tools/gradle.json",
      "bytes": 25288,
      "sha256": "072735aa4a42ef4d69d2b46a4205e2a94577ee1a428b9aa6e0702220df37ce0c"
    },
    {
      "id": "scala",
      "name": "Scala",
      "categoryId": "java",
      "platforms": [
        "windows",
        "macos",
        "linux"
      ],
      "sourceCount": 3,
      "bestQualityScore": 100,
      "path": "data/online/tools/scala.json",
      "bytes": 25323,
      "sha256": "15657874266a9c7021f3b9f4ee4c39aca570d4aaa900bfdf22fca7ab3bdae91a"
    },
    {
      "id": "sbt",
      "name": "sbt",
      "categoryId": "java",
      "platforms": [
        "windows",
        "macos",
        "linux"
      ],
      "sourceCount": 4,
      "bestQualityScore": 100,
      "path": "data/online/tools/sbt.json",
      "bytes": 37765,
      "sha256": "5d5e674531ebb23009fcda63cf1de728fb289c6f839067813564f5983cfdce9c"
    },
    {
      "id": "cmake",
      "name": "CMake",
      "categoryId": "cpp",
      "platforms": [
        "windows",
        "macos",
        "linux"
      ],
      "sourceCount": 5,
      "bestQualityScore": 100,
      "path": "data/online/tools/cmake.json",
      "bytes": 89426,
      "sha256": "8569391b7da9533f0289938baaba3e820b0e0de505f6a860fd1a3ce153fd75fd"
    },
    {
      "id": "ninja",
      "name": "Ninja",
      "categoryId": "cpp",
      "platforms": [
        "windows",
        "macos",
        "linux"
      ],
      "sourceCount": 5,
      "bestQualityScore": 100,
      "path": "data/online/tools/ninja.json",
      "bytes": 69182,
      "sha256": "48e3ade4b157adef0f27665fe9ab6a76bb37f258b7c6cf62d2526402fb303fca"
    },
    {
      "id": "llvm",
      "name": "LLVM",
      "categoryId": "cpp",
      "platforms": [
        "windows",
        "macos",
        "linux"
      ],
      "sourceCount": 4,
      "bestQualityScore": 100,
      "path": "data/online/tools/llvm.json",
      "bytes": 40861,
      "sha256": "d9b289fe9f55c61210156bca9fd4c37ebc0f6094895917a70e52fb0dacd86c7f"
    },
    {
      "id": "vs_build_tools",
      "name": "Visual Studio Build Tools",
      "categoryId": "cpp",
      "platforms": [
        "windows"
      ],
      "sourceCount": 1,
      "bestQualityScore": 100,
      "path": "data/online/tools/vs_build_tools.json",
      "bytes": 15719,
      "sha256": "30dad7c88cd265b063dcb51054d80d0bb2c45efd2f6c8f55105d0a515713c867"
    },
    {
      "id": "visual_studio_community",
      "name": "Visual Studio Community",
      "categoryId": "cpp",
      "platforms": [
        "windows"
      ],
      "sourceCount": 1,
      "bestQualityScore": 100,
      "path": "data/online/tools/visual_studio_community.json",
      "bytes": 16154,
      "sha256": "d28658b4fbbce9948f8fec33aa8e30eb57f5a5d9ab4c2e1ca45871176b537fcf"
    },
    {
      "id": "msys2",
      "name": "MSYS2",
      "categoryId": "cpp",
      "platforms": [
        "windows"
      ],
      "sourceCount": 1,
      "bestQualityScore": 100,
      "path": "data/online/tools/msys2.json",
      "bytes": 15096,
      "sha256": "e6a853be16aec05f79fc63dcfc51ad1d0a4da57913573f8422f7ac1e320fca39"
    },
    {
      "id": "docker_desktop",
      "name": "Docker Desktop",
      "categoryId": "container",
      "platforms": [
        "windows",
        "macos"
      ],
      "sourceCount": 3,
      "bestQualityScore": 100,
      "path": "data/online/tools/docker_desktop.json",
      "bytes": 35009,
      "sha256": "c7f2f421bd63c54b4267aede948ac3659743df6d81d341566f8e0e018fcf0f57"
    },
    {
      "id": "podman",
      "name": "Podman",
      "categoryId": "container",
      "platforms": [
        "windows",
        "macos",
        "linux"
      ],
      "sourceCount": 4,
      "bestQualityScore": 100,
      "path": "data/online/tools/podman.json",
      "bytes": 76440,
      "sha256": "adc1ca7281b6bf0775826385587873e95394a8ef54b53c72b5162119239172bd"
    },
    {
      "id": "rancher_desktop",
      "name": "Rancher Desktop",
      "categoryId": "container",
      "platforms": [
        "windows"
      ],
      "sourceCount": 1,
      "bestQualityScore": 100,
      "path": "data/online/tools/rancher_desktop.json",
      "bytes": 14909,
      "sha256": "77ca25542ba606f28b61d1236dbcbb2985358d07ed53b209325ff2d30e201e6c"
    },
    {
      "id": "kubectl",
      "name": "kubectl",
      "categoryId": "container",
      "platforms": [
        "windows",
        "macos",
        "linux"
      ],
      "sourceCount": 4,
      "bestQualityScore": 100,
      "path": "data/online/tools/kubectl.json",
      "bytes": 42975,
      "sha256": "fd3cdc7d5d3071e0b3e0334b761d320f3e465f08a3c90dc0dcb30603b1fb6a6c"
    },
    {
      "id": "helm",
      "name": "Helm",
      "categoryId": "container",
      "platforms": [
        "windows",
        "macos",
        "linux"
      ],
      "sourceCount": 5,
      "bestQualityScore": 100,
      "path": "data/online/tools/helm.json",
      "bytes": 89062,
      "sha256": "479aabdc29070f560c19112c5a675b91cf17eda7273ba7f1873260476ff6a48a"
    },
    {
      "id": "minikube",
      "name": "minikube",
      "categoryId": "container",
      "platforms": [
        "windows",
        "macos",
        "linux"
      ],
      "sourceCount": 5,
      "bestQualityScore": 100,
      "path": "data/online/tools/minikube.json",
      "bytes": 89224,
      "sha256": "773169be448c7c94ab9fc94bc1cfbade4ded061c0002285f496da17af1d01255"
    },
    {
      "id": "kind",
      "name": "kind",
      "categoryId": "container",
      "platforms": [
        "windows",
        "macos",
        "linux"
      ],
      "sourceCount": 5,
      "bestQualityScore": 100,
      "path": "data/online/tools/kind.json",
      "bytes": 82835,
      "sha256": "ed3cc6af75ffcfd3be1bc3b3c4dd74176f6ef16e37ba488dd0f60dcb451ea794"
    },
    {
      "id": "terraform",
      "name": "Terraform",
      "categoryId": "devops",
      "platforms": [
        "windows",
        "macos",
        "linux"
      ],
      "sourceCount": 4,
      "bestQualityScore": 100,
      "path": "data/online/tools/terraform.json",
      "bytes": 55012,
      "sha256": "fa48609423d6caf8b2b11596c72c3d920aae69be10508f5edca182df1a4810a1"
    },
    {
      "id": "opentofu",
      "name": "OpenTofu",
      "categoryId": "devops",
      "platforms": [
        "windows",
        "macos",
        "linux"
      ],
      "sourceCount": 5,
      "bestQualityScore": 100,
      "path": "data/online/tools/opentofu.json",
      "bytes": 90486,
      "sha256": "c2e08dd30935f912b471738db9377ab10ea887dea8a45bb94396d76ee30bad07"
    },
    {
      "id": "packer",
      "name": "Packer",
      "categoryId": "devops",
      "platforms": [
        "windows",
        "macos",
        "linux"
      ],
      "sourceCount": 4,
      "bestQualityScore": 100,
      "path": "data/online/tools/packer.json",
      "bytes": 82610,
      "sha256": "532daf1a907e14acd31251a899d5a820a0c7a2570b4ec167ea5be2c391569e54"
    },
    {
      "id": "vagrant",
      "name": "Vagrant",
      "categoryId": "devops",
      "platforms": [
        "windows",
        "macos",
        "linux"
      ],
      "sourceCount": 5,
      "bestQualityScore": 100,
      "path": "data/online/tools/vagrant.json",
      "bytes": 92977,
      "sha256": "e78bb3160605340182707da001f002922556da77c01b26945dd7d13430196f08"
    },
    {
      "id": "pulumi",
      "name": "Pulumi",
      "categoryId": "devops",
      "platforms": [
        "windows",
        "macos",
        "linux"
      ],
      "sourceCount": 5,
      "bestQualityScore": 100,
      "path": "data/online/tools/pulumi.json",
      "bytes": 88538,
      "sha256": "8d881feafbbf3382e6b9bbdaddce8a1cb4e46dbd257bf77853671375aacafb1d"
    },
    {
      "id": "ansible",
      "name": "Ansible",
      "categoryId": "devops",
      "platforms": [
        "windows",
        "macos",
        "linux"
      ],
      "sourceCount": 1,
      "bestQualityScore": 100,
      "path": "data/online/tools/ansible.json",
      "bytes": 7832,
      "sha256": "73ff94997d5355574aa2727a9d5bee71730eace8a0bccfdf4daf3fe343d1b331"
    },
    {
      "id": "aws_cli",
      "name": "AWS CLI",
      "categoryId": "cloud",
      "platforms": [
        "windows",
        "macos",
        "linux"
      ],
      "sourceCount": 4,
      "bestQualityScore": 100,
      "path": "data/online/tools/aws_cli.json",
      "bytes": 40404,
      "sha256": "4d9572809a2d7b915675df80ed0ea041c221113e9097403f2c65741da6dc232c"
    },
    {
      "id": "azure_cli",
      "name": "Azure CLI",
      "categoryId": "cloud",
      "platforms": [
        "windows",
        "macos",
        "linux"
      ],
      "sourceCount": 4,
      "bestQualityScore": 100,
      "path": "data/online/tools/azure_cli.json",
      "bytes": 39635,
      "sha256": "1640ddb9f8a5d4fc54deba05655afb0b66742d6edb8f7564baab5db525953f74"
    },
    {
      "id": "google_cloud_sdk",
      "name": "Google Cloud SDK",
      "categoryId": "cloud",
      "platforms": [
        "windows"
      ],
      "sourceCount": 3,
      "bestQualityScore": 100,
      "path": "data/online/tools/google_cloud_sdk.json",
      "bytes": 28291,
      "sha256": "a67437194ed4244a7ce399267b9fcfd2dd55abaf59e49c133d2129891218f0aa"
    },
    {
      "id": "cloudflared",
      "name": "cloudflared",
      "categoryId": "cloud",
      "platforms": [
        "windows",
        "macos",
        "linux"
      ],
      "sourceCount": 5,
      "bestQualityScore": 100,
      "path": "data/online/tools/cloudflared.json",
      "bytes": 90577,
      "sha256": "ed90e7bc558300454eb4573fe5e8e97baeba90973f9878cc21859b26df78ace2"
    },
    {
      "id": "postman",
      "name": "Postman",
      "categoryId": "api",
      "platforms": [
        "windows",
        "macos"
      ],
      "sourceCount": 4,
      "bestQualityScore": 100,
      "path": "data/online/tools/postman.json",
      "bytes": 37012,
      "sha256": "87550e44608bee6f3424acc2ae9eec1ec9c279597deb56609dac9e73fac68eaf"
    },
    {
      "id": "insomnia",
      "name": "Insomnia",
      "categoryId": "api",
      "platforms": [
        "windows",
        "macos",
        "linux"
      ],
      "sourceCount": 4,
      "bestQualityScore": 100,
      "path": "data/online/tools/insomnia.json",
      "bytes": 75500,
      "sha256": "f63911e8910adddc7e835856b3d4f16f28d17afc07fadc9dab87f74a0b59064d"
    },
    {
      "id": "bruno",
      "name": "Bruno",
      "categoryId": "api",
      "platforms": [
        "windows",
        "macos",
        "linux"
      ],
      "sourceCount": 5,
      "bestQualityScore": 100,
      "path": "data/online/tools/bruno.json",
      "bytes": 86601,
      "sha256": "f266446469cded9a041c11dbadc39bf5854126697fa67f5e7e64d48e91930ac3"
    },
    {
      "id": "httpie",
      "name": "HTTPie",
      "categoryId": "api",
      "platforms": [
        "windows",
        "macos",
        "linux"
      ],
      "sourceCount": 4,
      "bestQualityScore": 100,
      "path": "data/online/tools/httpie.json",
      "bytes": 40852,
      "sha256": "c6a1778fb0ad9775c7c0295ce11fc5d4c12e4ecef549d7b61c1a2ee90705da5e"
    },
    {
      "id": "pgadmin",
      "name": "pgAdmin",
      "categoryId": "database",
      "platforms": [
        "windows"
      ],
      "sourceCount": 1,
      "bestQualityScore": 100,
      "path": "data/online/tools/pgadmin.json",
      "bytes": 13411,
      "sha256": "c1e0db59440f9c6e37b7b39b7b13c4ff46732e9c0cc2a8180aaa44256f297fd3"
    },
    {
      "id": "mysql",
      "name": "MySQL",
      "categoryId": "database",
      "platforms": [
        "windows",
        "macos",
        "linux"
      ],
      "sourceCount": 4,
      "bestQualityScore": 100,
      "path": "data/online/tools/mysql.json",
      "bytes": 33153,
      "sha256": "8a92d90692af5d405bf275b6e1088b5a5f6b7bb92b9bf5f1a7771019472c7e62"
    },
    {
      "id": "mysql_workbench",
      "name": "MySQL Workbench",
      "categoryId": "database",
      "platforms": [
        "windows"
      ],
      "sourceCount": 1,
      "bestQualityScore": 100,
      "path": "data/online/tools/mysql_workbench.json",
      "bytes": 9892,
      "sha256": "cb0b78501a54ce66f9660e025ecac003a0c81f50f39bdbb1d040d1784a83fbe3"
    },
    {
      "id": "mariadb",
      "name": "MariaDB",
      "categoryId": "database",
      "platforms": [
        "windows",
        "macos",
        "linux"
      ],
      "sourceCount": 4,
      "bestQualityScore": 100,
      "path": "data/online/tools/mariadb.json",
      "bytes": 38299,
      "sha256": "42156f5425bfc57742e3e9e0fe8c242261ed97325797738f68a11645b8721e22"
    },
    {
      "id": "mongodb_compass",
      "name": "MongoDB Compass",
      "categoryId": "database",
      "platforms": [
        "windows"
      ],
      "sourceCount": 1,
      "bestQualityScore": 100,
      "path": "data/online/tools/mongodb_compass.json",
      "bytes": 16503,
      "sha256": "de71fa8b6944e8755f47b569a73a0249ef612cd93e7b423c2cb2efbc8f353c0c"
    },
    {
      "id": "redis",
      "name": "Redis",
      "categoryId": "database",
      "platforms": [
        "windows",
        "macos",
        "linux"
      ],
      "sourceCount": 4,
      "bestQualityScore": 100,
      "path": "data/online/tools/redis.json",
      "bytes": 29097,
      "sha256": "bf67f0a1b9e1095bbcaf14466c9ec6abe20dd7eb668d504de5457c4e9b2fe9ed"
    },
    {
      "id": "sqlite_browser",
      "name": "DB Browser for SQLite",
      "categoryId": "database",
      "platforms": [
        "windows"
      ],
      "sourceCount": 1,
      "bestQualityScore": 100,
      "path": "data/online/tools/sqlite_browser.json",
      "bytes": 10733,
      "sha256": "fa2df8317c80b55211ae6cdac9293e744a9c99945e549f4bf98679890934f7ae"
    },
    {
      "id": "dbeaver",
      "name": "DBeaver Community",
      "categoryId": "database",
      "platforms": [
        "windows",
        "macos",
        "linux"
      ],
      "sourceCount": 5,
      "bestQualityScore": 100,
      "path": "data/online/tools/dbeaver.json",
      "bytes": 90148,
      "sha256": "7353ea48036865842b25d10c2a80e2c08189616cb3eaa201c1f40cf9e438beb0"
    },
    {
      "id": "beekeeper_studio",
      "name": "Beekeeper Studio",
      "categoryId": "database",
      "platforms": [
        "windows",
        "macos",
        "linux"
      ],
      "sourceCount": 4,
      "bestQualityScore": 100,
      "path": "data/online/tools/beekeeper_studio.json",
      "bytes": 88391,
      "sha256": "1e5260133174579a21f8ab98d13b510f7ab1b665fef3f1df4a2e8c1bd8571613"
    },
    {
      "id": "android_studio",
      "name": "Android Studio",
      "categoryId": "mobile",
      "platforms": [
        "windows",
        "macos"
      ],
      "sourceCount": 3,
      "bestQualityScore": 100,
      "path": "data/online/tools/android_studio.json",
      "bytes": 37736,
      "sha256": "64e66ee93d7b5740d00e4cec2a552533382ce3f8bb22d3383b9d02df3bb9a19e"
    },
    {
      "id": "android_platform_tools",
      "name": "Android SDK Platform-Tools",
      "categoryId": "mobile",
      "platforms": [
        "windows",
        "macos"
      ],
      "sourceCount": 4,
      "bestQualityScore": 100,
      "path": "data/online/tools/android_platform_tools.json",
      "bytes": 34068,
      "sha256": "1737214eaea07a1cc5e897e40158cc891691299c502a9e5da82dccd31d89dc6d"
    },
    {
      "id": "flutter",
      "name": "Flutter",
      "categoryId": "mobile",
      "platforms": [
        "windows",
        "macos",
        "linux"
      ],
      "sourceCount": 4,
      "bestQualityScore": 100,
      "path": "data/online/tools/flutter.json",
      "bytes": 31006,
      "sha256": "edea020f2482af168bc75775b32a5d3ae28f5e6e956ff973c90378d00f86ab24"
    },
    {
      "id": "wireshark",
      "name": "Wireshark",
      "categoryId": "security",
      "platforms": [
        "windows",
        "macos",
        "linux"
      ],
      "sourceCount": 4,
      "bestQualityScore": 100,
      "path": "data/online/tools/wireshark.json",
      "bytes": 39805,
      "sha256": "06eacd47f8828134da3ab53d2eda698215ea54fdf305eec52dbb0cc9b2a381c5"
    },
    {
      "id": "mitmproxy",
      "name": "mitmproxy",
      "categoryId": "security",
      "platforms": [
        "windows",
        "macos",
        "linux"
      ],
      "sourceCount": 5,
      "bestQualityScore": 100,
      "path": "data/online/tools/mitmproxy.json",
      "bytes": 53736,
      "sha256": "8a00e6cb5bf4302f22df0da6fbfd120e8b1da7b350123cf8e501b7e66f550bb6"
    },
    {
      "id": "nmap",
      "name": "Nmap",
      "categoryId": "security",
      "platforms": [
        "windows",
        "macos",
        "linux"
      ],
      "sourceCount": 4,
      "bestQualityScore": 100,
      "path": "data/online/tools/nmap.json",
      "bytes": 32528,
      "sha256": "9a6169b5147cc823ad505fd44d33d6cf3e25dc90b6521d490b9c0ba36d2b2e3e"
    },
    {
      "id": "sysinternals_suite",
      "name": "Sysinternals Suite",
      "categoryId": "security",
      "platforms": [
        "windows"
      ],
      "sourceCount": 1,
      "bestQualityScore": 100,
      "path": "data/online/tools/sysinternals_suite.json",
      "bytes": 7081,
      "sha256": "621304c30a27274e804c577b498f141d4ccb63b5b5100d2611d3667d9c589585"
    },
    {
      "id": "process_explorer",
      "name": "Process Explorer",
      "categoryId": "security",
      "platforms": [
        "windows"
      ],
      "sourceCount": 1,
      "bestQualityScore": 100,
      "path": "data/online/tools/process_explorer.json",
      "bytes": 7196,
      "sha256": "5f46262c2db9135d1d9e38c13e6960a5d3d560d5ca88cfc7f4db4c960a657ccd"
    },
    {
      "id": "sysmon",
      "name": "Sysmon",
      "categoryId": "security",
      "platforms": [
        "windows"
      ],
      "sourceCount": 1,
      "bestQualityScore": 100,
      "path": "data/online/tools/sysmon.json",
      "bytes": 8044,
      "sha256": "6c4133a2acafbd6cf7a262ec6742f6df742a726a9df2ae635b71612c1ab9dafb"
    },
    {
      "id": "r",
      "name": "R",
      "categoryId": "data",
      "platforms": [
        "windows",
        "macos",
        "linux"
      ],
      "sourceCount": 3,
      "bestQualityScore": 100,
      "path": "data/online/tools/r.json",
      "bytes": 34538,
      "sha256": "fa1d88369572092f31e26d1f88ab16cfdbf48869509038aad2313da9efcca8b5"
    },
    {
      "id": "rstudio",
      "name": "RStudio Desktop",
      "categoryId": "data",
      "platforms": [
        "windows",
        "macos"
      ],
      "sourceCount": 3,
      "bestQualityScore": 100,
      "path": "data/online/tools/rstudio.json",
      "bytes": 33899,
      "sha256": "0b7b8ba707c2eb8420e676894eab983deb6ea90409719781c74daa9297abe5c0"
    },
    {
      "id": "julia",
      "name": "Julia",
      "categoryId": "data",
      "platforms": [
        "windows",
        "macos",
        "linux"
      ],
      "sourceCount": 4,
      "bestQualityScore": 100,
      "path": "data/online/tools/julia.json",
      "bytes": 41504,
      "sha256": "e8d4550ca561f7f47177c65ca7f7c81fbed6d80050d5270fb9d922ff8d040352"
    },
    {
      "id": "quarto",
      "name": "Quarto",
      "categoryId": "data",
      "platforms": [
        "windows",
        "macos",
        "linux"
      ],
      "sourceCount": 5,
      "bestQualityScore": 100,
      "path": "data/online/tools/quarto.json",
      "bytes": 120735,
      "sha256": "85dcde405c0bc0c13ca18ec3bf40a727296eed6b67016ca2468189c1b642fbcb"
    },
    {
      "id": "vercel_cli",
      "name": "Vercel CLI",
      "categoryId": "web",
      "platforms": [
        "windows",
        "macos",
        "linux"
      ],
      "sourceCount": 1,
      "bestQualityScore": 100,
      "path": "data/online/tools/vercel_cli.json",
      "bytes": 36898,
      "sha256": "b89ee4c0c540720586650bef2f62a2adbd85feaf924c21e3944df69b2b39d2fd"
    },
    {
      "id": "netlify_cli",
      "name": "Netlify CLI",
      "categoryId": "web",
      "platforms": [
        "windows",
        "macos",
        "linux"
      ],
      "sourceCount": 1,
      "bestQualityScore": 75,
      "path": "data/online/tools/netlify_cli.json",
      "bytes": 14673,
      "sha256": "9ec27b41c0a15266dce9311caecd916529792b4b0a6b752fa42aa3f32a5fb38a"
    },
    {
      "id": "heroku_cli",
      "name": "Heroku CLI",
      "categoryId": "web",
      "platforms": [
        "windows"
      ],
      "sourceCount": 1,
      "bestQualityScore": 100,
      "path": "data/online/tools/heroku_cli.json",
      "bytes": 8210,
      "sha256": "eb0cc7ce136d10a5e4a70f7865f43736f6dbf357beca680348e0e0589909e644"
    },
    {
      "id": "stripe_cli",
      "name": "Stripe CLI",
      "categoryId": "web",
      "platforms": [
        "windows",
        "macos",
        "linux"
      ],
      "sourceCount": 3,
      "bestQualityScore": 100,
      "path": "data/online/tools/stripe_cli.json",
      "bytes": 69761,
      "sha256": "4a666aea23d57569f198c68cda375c4de0b056a2530704a4bc9c0510e1953e9a"
    },
    {
      "id": "supabase_cli",
      "name": "Supabase CLI",
      "categoryId": "web",
      "platforms": [
        "windows",
        "macos",
        "linux"
      ],
      "sourceCount": 3,
      "bestQualityScore": 100,
      "path": "data/online/tools/supabase_cli.json",
      "bytes": 64267,
      "sha256": "6f22f1b15b3e29cc23277dd801f0776b7271a18223053610339bf93aea075189"
    },
    {
      "id": "prisma_cli",
      "name": "Prisma CLI",
      "categoryId": "web",
      "platforms": [
        "windows",
        "macos",
        "linux"
      ],
      "sourceCount": 1,
      "bestQualityScore": 75,
      "path": "data/online/tools/prisma_cli.json",
      "bytes": 16014,
      "sha256": "4a3c60023d3abf7af17969605ec2a3a3f4344f556a4750ecb0dbfc0cf31cd3d5"
    },
    {
      "id": "php",
      "name": "PHP",
      "categoryId": "php",
      "platforms": [
        "windows",
        "macos",
        "linux"
      ],
      "sourceCount": 3,
      "bestQualityScore": 100,
      "path": "data/online/tools/php.json",
      "bytes": 26354,
      "sha256": "49e1a89e6ca8e99240d0848f3d13923c7a10e3aa23663638699e3b3d9a518d53"
    },
    {
      "id": "composer",
      "name": "Composer",
      "categoryId": "php",
      "platforms": [
        "windows",
        "macos",
        "linux"
      ],
      "sourceCount": 3,
      "bestQualityScore": 100,
      "path": "data/online/tools/composer.json",
      "bytes": 20614,
      "sha256": "bdada03007f9116bc6f7d8b6e6ab99d64f3c2d0ae8b4620276aabe75f8d94926"
    },
    {
      "id": "ruby",
      "name": "RubyInstaller with Devkit",
      "categoryId": "ruby",
      "platforms": [
        "windows",
        "macos",
        "linux"
      ],
      "sourceCount": 4,
      "bestQualityScore": 100,
      "path": "data/online/tools/ruby.json",
      "bytes": 35179,
      "sha256": "38f7e77da12a28f2d1803509eff715eaf5f3fb040032395dfc53f680369b18f7"
    },
    {
      "id": "erlang",
      "name": "Erlang/OTP",
      "categoryId": "functional",
      "platforms": [
        "windows",
        "macos",
        "linux"
      ],
      "sourceCount": 4,
      "bestQualityScore": 100,
      "path": "data/online/tools/erlang.json",
      "bytes": 41265,
      "sha256": "74f21c49803bf2df2f9b2576a8e48ea2a22d825c2a1acd93857d2dfe2c9f654b"
    },
    {
      "id": "elixir",
      "name": "Elixir",
      "categoryId": "functional",
      "platforms": [
        "windows",
        "macos",
        "linux"
      ],
      "sourceCount": 3,
      "bestQualityScore": 100,
      "path": "data/online/tools/elixir.json",
      "bytes": 26572,
      "sha256": "e99c39295713f650da6aa4e5bdd490266b94320b38f0252ae17f809cc149b569"
    },
    {
      "id": "godot",
      "name": "Godot Engine",
      "categoryId": "game",
      "platforms": [
        "windows",
        "macos",
        "linux"
      ],
      "sourceCount": 5,
      "bestQualityScore": 100,
      "path": "data/online/tools/godot.json",
      "bytes": 91831,
      "sha256": "95e11c43e9db3adf6c90cae9f96feea2a0687f5a3b6360e3343957e07e72f332"
    },
    {
      "id": "unity_hub",
      "name": "Unity Hub",
      "categoryId": "game",
      "platforms": [
        "windows",
        "macos"
      ],
      "sourceCount": 3,
      "bestQualityScore": 100,
      "path": "data/online/tools/unity_hub.json",
      "bytes": 27516,
      "sha256": "9bc74fb0b4eb92c1a4d3a07d812ca64a22942b06d6ac623a996c56a53261dfe1"
    },
    {
      "id": "blender",
      "name": "Blender",
      "categoryId": "game",
      "platforms": [
        "windows",
        "macos"
      ],
      "sourceCount": 4,
      "bestQualityScore": 100,
      "path": "data/online/tools/blender.json",
      "bytes": 40112,
      "sha256": "e9dbbae7f93bea049ff4afb38660e6f23381b4d83b6c1035f5022d9058710f8e"
    },
    {
      "id": "pandoc",
      "name": "Pandoc",
      "categoryId": "docs",
      "platforms": [
        "windows",
        "macos",
        "linux"
      ],
      "sourceCount": 5,
      "bestQualityScore": 100,
      "path": "data/online/tools/pandoc.json",
      "bytes": 88981,
      "sha256": "94f525f3dd79cb0453449ee598973398a5dc4a5c3f27fc1822a889f1248dc6a4"
    },
    {
      "id": "hugo",
      "name": "Hugo",
      "categoryId": "docs",
      "platforms": [
        "windows",
        "macos",
        "linux"
      ],
      "sourceCount": 5,
      "bestQualityScore": 100,
      "path": "data/online/tools/hugo.json",
      "bytes": 93764,
      "sha256": "a7785374d8eb74dd155df4abb08200839212469c4b93f6f12f7df39dcfe64b7f"
    },
    {
      "id": "mkdocs",
      "name": "MkDocs",
      "categoryId": "docs",
      "platforms": [
        "windows",
        "macos",
        "linux"
      ],
      "sourceCount": 2,
      "bestQualityScore": 100,
      "path": "data/online/tools/mkdocs.json",
      "bytes": 21661,
      "sha256": "968c7669a6f389f38796c34f8ef3e9a6eb9376bd65fbbd751000d3c62bda789a"
    },
    {
      "id": "clojure",
      "name": "Clojure CLI",
      "categoryId": "java",
      "platforms": [
        "windows"
      ],
      "sourceCount": 0,
      "bestQualityScore": 0,
      "path": "data/online/tools/clojure.json",
      "bytes": 1634,
      "sha256": "03593a2d4159ccdc4329c2e52b9067828a20700ff26305a03ee9f293fbbe36de"
    },
    {
      "id": "ddev",
      "name": "DDEV",
      "categoryId": "container",
      "platforms": [
        "windows"
      ],
      "sourceCount": 0,
      "bestQualityScore": 0,
      "path": "data/online/tools/ddev.json",
      "bytes": 1605,
      "sha256": "1378cef627e8228a5031ffbec240311c780b4f600cabe234ee86261edf1aa7c4"
    },
    {
      "id": "wrangler",
      "name": "Wrangler",
      "categoryId": "cloud",
      "platforms": [
        "windows"
      ],
      "sourceCount": 0,
      "bestQualityScore": 0,
      "path": "data/online/tools/wrangler.json",
      "bytes": 1727,
      "sha256": "ba09fc4cfed70ad7237d72b8b62ecff2f4342c34a74e08f9fb2f3b98b0448056"
    },
    {
      "id": "doppler",
      "name": "Doppler CLI",
      "categoryId": "cloud",
      "platforms": [
        "windows"
      ],
      "sourceCount": 0,
      "bestQualityScore": 0,
      "path": "data/online/tools/doppler.json",
      "bytes": 1648,
      "sha256": "010858f6ef4c1abe921d5b239ba0da203aa96d9bd9148173c9d931215def68ef"
    },
    {
      "id": "graphql_playground",
      "name": "GraphQL Playground",
      "categoryId": "api",
      "platforms": [
        "windows"
      ],
      "sourceCount": 0,
      "bestQualityScore": 0,
      "path": "data/online/tools/graphql_playground.json",
      "bytes": 1498,
      "sha256": "8f3a5de807f8301429e400b047484d590c8bfb51789a6d18b2ea18ffbe02b54b"
    },
    {
      "id": "graphiql",
      "name": "GraphiQL",
      "categoryId": "api",
      "platforms": [
        "windows"
      ],
      "sourceCount": 0,
      "bestQualityScore": 0,
      "path": "data/online/tools/graphiql.json",
      "bytes": 1428,
      "sha256": "267298f165ad2fa660c7ed60660738e56c83fd030c289d6142cca26bc3fa41e9"
    },
    {
      "id": "postgresql",
      "name": "PostgreSQL",
      "categoryId": "database",
      "platforms": [
        "windows"
      ],
      "sourceCount": 0,
      "bestQualityScore": 0,
      "path": "data/online/tools/postgresql.json",
      "bytes": 1677,
      "sha256": "f8869ae96ba1927d624a7f63d2d8ad50030ddc9805545d39c5c51ef5058813f3"
    },
    {
      "id": "dart",
      "name": "Dart SDK",
      "categoryId": "mobile",
      "platforms": [
        "windows"
      ],
      "sourceCount": 0,
      "bestQualityScore": 0,
      "path": "data/online/tools/dart.json",
      "bytes": 1611,
      "sha256": "6945ca3524da0ad260711f39039d7e4ce05f4c30e1fbb7b8c1b39ccbb0309142"
    },
    {
      "id": "ngrok",
      "name": "ngrok",
      "categoryId": "web",
      "platforms": [
        "windows"
      ],
      "sourceCount": 0,
      "bestQualityScore": 0,
      "path": "data/online/tools/ngrok.json",
      "bytes": 1585,
      "sha256": "e77e7c25cbdba8eed653631525476c68e8f2f61e4ee4dccb8ab6ddbc89168c71"
    },
    {
      "id": "active_state_cli",
      "name": "ActiveState CLI",
      "categoryId": "ruby",
      "platforms": [
        "windows"
      ],
      "sourceCount": 0,
      "bestQualityScore": 0,
      "path": "data/online/tools/active_state_cli.json",
      "bytes": 1784,
      "sha256": "69443da858b9b2f92a41897449534c0a6a0fae5558e3214b96e331e9a10f4b85"
    },
    {
      "id": "haskell_ghcup",
      "name": "GHCup",
      "categoryId": "functional",
      "platforms": [
        "windows"
      ],
      "sourceCount": 0,
      "bestQualityScore": 0,
      "path": "data/online/tools/haskell_ghcup.json",
      "bytes": 1689,
      "sha256": "15306718005f2c57bc58e57227ddbcdccb939de8f297929e9e2b4c9baa6c5d16"
    }
  ]
}
