{
  "schemaVersion": 1,
  "generatedAt": "2026-06-13T09:35:01.696Z",
  "status": "ok",
  "tool": {
    "id": "rancher_desktop",
    "name": "Rancher Desktop",
    "categoryId": "container",
    "aliases": [],
    "tags": [],
    "platforms": [
      "windows"
    ],
    "lifecycle": {
      "status": "active",
      "deprecated": false,
      "replacedBy": null
    },
    "links": {
      "homepage": "https://rancherdesktop.io/",
      "download": "https://rancherdesktop.io/",
      "releases": null,
      "docs": null
    },
    "descriptions": {
      "short": null,
      "long": null,
      "source": "catalog",
      "homepage": "https://rancherdesktop.io/",
      "lastUpdatedAt": null
    },
    "usage": {
      "primaryUseCases": [
        "container"
      ],
      "keywords": [
        "rancher_desktop",
        "Rancher Desktop",
        "official-download",
        "winget"
      ],
      "relatedTools": []
    },
    "notes": {
      "install": [],
      "upgrade": [],
      "knownIssues": []
    },
    "detection": {
      "commands": []
    },
    "verify": {
      "commands": []
    },
    "dependencies": {
      "required": false,
      "requiredBySuites": [],
      "dependsOn": [],
      "optionalDependencies": []
    },
    "risk": {
      "requiresAdmin": false,
      "portable": false,
      "systemCritical": false
    },
    "quality": {
      "confidence": "high",
      "score": 100
    },
    "sources": [
      {
        "id": "winget",
        "manager": "winget",
        "packageId": "SUSE.RancherDesktop",
        "platforms": [
          "windows"
        ],
        "official": true,
        "priority": 10,
        "scan": {
          "status": "ok",
          "scannedAt": "2026-06-13T09:34:29.716Z",
          "errors": []
        },
        "package": {
          "name": "Rancher Desktop",
          "publisher": "SUSE",
          "author": "rancher-sandbox",
          "description": null,
          "license": "Apache-2.0",
          "licenseUrl": "https://github.com/rancher-sandbox/rancher-desktop/blob/HEAD/LICENSE",
          "tags": []
        },
        "links": {
          "homepage": "https://rancherdesktop.io/",
          "download": "https://github.com/rancher-sandbox/rancher-desktop/releases/download/v1.22.3/Rancher.Desktop.Setup.1.22.3.msi",
          "releases": "https://github.com/rancher-sandbox/rancher-desktop/releases/tag/v1.22.3",
          "docs": null
        },
        "descriptions": {
          "short": null,
          "long": null,
          "source": "winget",
          "homepage": "https://rancherdesktop.io/",
          "lastUpdatedAt": "2026-06-13T09:34:29.716Z"
        },
        "usage": {
          "primaryUseCases": [
            "container"
          ],
          "keywords": [
            "rancher_desktop",
            "Rancher Desktop",
            "winget"
          ],
          "relatedTools": []
        },
        "notes": {
          "install": [],
          "upgrade": [],
          "knownIssues": []
        },
        "versions": [
          {
            "version": "1.22.3",
            "channel": "stable",
            "latest": true,
            "prerelease": false,
            "lts": null,
            "releaseDate": null,
            "eolDate": null,
            "changelogUrl": null
          },
          {
            "version": "1.22.2",
            "channel": "stable",
            "latest": false,
            "prerelease": false,
            "lts": null,
            "releaseDate": null,
            "eolDate": null,
            "changelogUrl": null
          },
          {
            "version": "1.22.0",
            "channel": "stable",
            "latest": false,
            "prerelease": false,
            "lts": null,
            "releaseDate": null,
            "eolDate": null,
            "changelogUrl": null
          },
          {
            "version": "1.21.0",
            "channel": "stable",
            "latest": false,
            "prerelease": false,
            "lts": null,
            "releaseDate": null,
            "eolDate": null,
            "changelogUrl": null
          },
          {
            "version": "1.20.1",
            "channel": "stable",
            "latest": false,
            "prerelease": false,
            "lts": null,
            "releaseDate": null,
            "eolDate": null,
            "changelogUrl": null
          },
          {
            "version": "1.20.0",
            "channel": "stable",
            "latest": false,
            "prerelease": false,
            "lts": null,
            "releaseDate": null,
            "eolDate": null,
            "changelogUrl": null
          },
          {
            "version": "1.19.3",
            "channel": "stable",
            "latest": false,
            "prerelease": false,
            "lts": null,
            "releaseDate": null,
            "eolDate": null,
            "changelogUrl": null
          },
          {
            "version": "1.19.2",
            "channel": "stable",
            "latest": false,
            "prerelease": false,
            "lts": null,
            "releaseDate": null,
            "eolDate": null,
            "changelogUrl": null
          },
          {
            "version": "1.19.1",
            "channel": "stable",
            "latest": false,
            "prerelease": false,
            "lts": null,
            "releaseDate": null,
            "eolDate": null,
            "changelogUrl": null
          },
          {
            "version": "1.19.0",
            "channel": "stable",
            "latest": false,
            "prerelease": false,
            "lts": null,
            "releaseDate": null,
            "eolDate": null,
            "changelogUrl": null
          },
          {
            "version": "1.18.2",
            "channel": "stable",
            "latest": false,
            "prerelease": false,
            "lts": null,
            "releaseDate": null,
            "eolDate": null,
            "changelogUrl": null
          },
          {
            "version": "1.18.0",
            "channel": "stable",
            "latest": false,
            "prerelease": false,
            "lts": null,
            "releaseDate": null,
            "eolDate": null,
            "changelogUrl": null
          },
          {
            "version": "1.17.1",
            "channel": "stable",
            "latest": false,
            "prerelease": false,
            "lts": null,
            "releaseDate": null,
            "eolDate": null,
            "changelogUrl": null
          },
          {
            "version": "1.17.0",
            "channel": "stable",
            "latest": false,
            "prerelease": false,
            "lts": null,
            "releaseDate": null,
            "eolDate": null,
            "changelogUrl": null
          },
          {
            "version": "1.15.1",
            "channel": "stable",
            "latest": false,
            "prerelease": false,
            "lts": null,
            "releaseDate": null,
            "eolDate": null,
            "changelogUrl": null
          },
          {
            "version": "1.14.2",
            "channel": "stable",
            "latest": false,
            "prerelease": false,
            "lts": null,
            "releaseDate": null,
            "eolDate": null,
            "changelogUrl": null
          },
          {
            "version": "1.13.1",
            "channel": "stable",
            "latest": false,
            "prerelease": false,
            "lts": null,
            "releaseDate": null,
            "eolDate": null,
            "changelogUrl": null
          },
          {
            "version": "1.13.0",
            "channel": "stable",
            "latest": false,
            "prerelease": false,
            "lts": null,
            "releaseDate": null,
            "eolDate": null,
            "changelogUrl": null
          },
          {
            "version": "1.12.3",
            "channel": "stable",
            "latest": false,
            "prerelease": false,
            "lts": null,
            "releaseDate": null,
            "eolDate": null,
            "changelogUrl": null
          },
          {
            "version": "1.11.1",
            "channel": "stable",
            "latest": false,
            "prerelease": false,
            "lts": null,
            "releaseDate": null,
            "eolDate": null,
            "changelogUrl": null
          },
          {
            "version": "1.11.0",
            "channel": "stable",
            "latest": false,
            "prerelease": false,
            "lts": null,
            "releaseDate": null,
            "eolDate": null,
            "changelogUrl": null
          },
          {
            "version": "1.10.0",
            "channel": "stable",
            "latest": false,
            "prerelease": false,
            "lts": null,
            "releaseDate": null,
            "eolDate": null,
            "changelogUrl": null
          },
          {
            "version": "1.9.1",
            "channel": "stable",
            "latest": false,
            "prerelease": false,
            "lts": null,
            "releaseDate": null,
            "eolDate": null,
            "changelogUrl": null
          },
          {
            "version": "1.8.1",
            "channel": "stable",
            "latest": false,
            "prerelease": false,
            "lts": null,
            "releaseDate": null,
            "eolDate": null,
            "changelogUrl": null
          },
          {
            "version": "1.7.0",
            "channel": "stable",
            "latest": false,
            "prerelease": false,
            "lts": null,
            "releaseDate": null,
            "eolDate": null,
            "changelogUrl": null
          },
          {
            "version": "1.6.2",
            "channel": "stable",
            "latest": false,
            "prerelease": false,
            "lts": null,
            "releaseDate": null,
            "eolDate": null,
            "changelogUrl": null
          },
          {
            "version": "1.6.1",
            "channel": "stable",
            "latest": false,
            "prerelease": false,
            "lts": null,
            "releaseDate": null,
            "eolDate": null,
            "changelogUrl": null
          },
          {
            "version": "1.6.0",
            "channel": "stable",
            "latest": false,
            "prerelease": false,
            "lts": null,
            "releaseDate": null,
            "eolDate": null,
            "changelogUrl": null
          },
          {
            "version": "1.5.1",
            "channel": "stable",
            "latest": false,
            "prerelease": false,
            "lts": null,
            "releaseDate": null,
            "eolDate": null,
            "changelogUrl": null
          },
          {
            "version": "1.5.0",
            "channel": "stable",
            "latest": false,
            "prerelease": false,
            "lts": null,
            "releaseDate": null,
            "eolDate": null,
            "changelogUrl": null
          }
        ],
        "downloads": [
          {
            "id": "default",
            "version": "1.22.3",
            "platform": "windows",
            "architecture": null,
            "type": "wix",
            "url": "https://github.com/rancher-sandbox/rancher-desktop/releases/download/v1.22.3/Rancher.Desktop.Setup.1.22.3.msi",
            "urlType": "direct-installer",
            "direct": true,
            "sha256": "d0918c3e99d2918d84d739e47df12964b2d75ccdf3f9da769b6d4b47ede187cf",
            "sizeBytes": null
          }
        ],
        "commands": [
          {
            "action": "install",
            "manager": "winget",
            "platform": "windows",
            "requiresAdmin": false,
            "supportsVersion": true,
            "shell": "argv",
            "command": [
              "winget",
              "install",
              "--id",
              "SUSE.RancherDesktop",
              "--exact",
              "--source",
              "winget",
              "--accept-package-agreements",
              "--accept-source-agreements"
            ],
            "template": [
              "winget",
              "install",
              "--id",
              "SUSE.RancherDesktop",
              "--exact",
              "--source",
              "--version",
              "{{version}}",
              "winget",
              "--accept-package-agreements",
              "--accept-source-agreements"
            ]
          },
          {
            "action": "update",
            "manager": "winget",
            "platform": "windows",
            "requiresAdmin": false,
            "supportsVersion": false,
            "shell": "argv",
            "command": [
              "winget",
              "upgrade",
              "--id",
              "SUSE.RancherDesktop",
              "--exact",
              "--source",
              "winget",
              "--accept-package-agreements",
              "--accept-source-agreements"
            ],
            "template": [
              "winget",
              "upgrade",
              "--id",
              "SUSE.RancherDesktop",
              "--exact",
              "--source",
              "winget",
              "--accept-package-agreements",
              "--accept-source-agreements"
            ]
          },
          {
            "action": "uninstall",
            "manager": "winget",
            "platform": "windows",
            "requiresAdmin": false,
            "supportsVersion": false,
            "shell": "argv",
            "command": [
              "winget",
              "uninstall",
              "--id",
              "SUSE.RancherDesktop",
              "--exact",
              "--source",
              "winget"
            ],
            "template": [
              "winget",
              "uninstall",
              "--id",
              "SUSE.RancherDesktop",
              "--exact",
              "--source",
              "winget"
            ]
          }
        ],
        "quality": {
          "confidence": "high",
          "score": 100,
          "official": true,
          "lastSuccessfulScanAt": "2026-06-13T09:34:29.716Z",
          "failureCount": 0,
          "staleAfterDays": 7
        },
        "dependencies": {
          "required": false,
          "requiredBySuites": [],
          "dependsOn": [],
          "optionalDependencies": []
        },
        "detection": {
          "commands": []
        },
        "verify": {
          "commands": []
        },
        "risk": {
          "requiresAdmin": false,
          "portable": false,
          "systemCritical": false
        }
      }
    ]
  }
}
